{
    "core:firstAid": {
        "base": {
            "effects": {
                "xtra": {
                    "type": "OPENING_BATTLE_SPELL",
                    "subtype": "spell.stoneSkin"
                }
            }
        },

        "basic": {
            "description": "{Basic First Aid}\n\nGives control of the first aid tent, heals up to {100 HP} to the first unit of the selected stack and cast {Stone Skin} at battle opening for {10 rounds}.",
            "effects": {
                "main": {
                    "val": 100
                },
                "xtra": {
                    "val": 10
                }
            }
        },

        "advanced": {
            "description": "{Advanced First Aid}\n\nGives control of the first aid tent, heals up to {225 HP} to the first unit of the selected stack and cast {Stone Skin} at battle opening for {25 rounds}.",
            "effects": {
                "main": {
                    "val": 225
                },
                "xtra": {
                    "val": 25
                }
            }
        },

        "expert": {
            "description": "{Expert First Aid}\n\nGives control of the first aid tent, heals up to {400 HP} to the first unit of the selected stack and cast {Stone Skin} at battle opening for {50 rounds}.",
            "effects": {
                "main": {
                    "val": 400
                },
                "xtra": {
                    "val": 50
                }
            }
        }
    }
}